yt2podcast/__init__.py
yt2podcast/__main__.py
yt2podcast/main.py
yt2podcast-0.4.dist-info/METADATA
yt2podcast-0.4.dist-info/WHEEL
yt2podcast-0.4.dist-info/top_level.txt
yt2podcast-0.4.dist-info/RECORD
