Metadata-Version: 2.1
Name: yt2podcast
Version: 0.4
Requires-Dist: requests
Requires-Dist: pyperclip
Requires-Dist: dropbox
